pyeuropeana/__init__.py
pyeuropeana/apis/__init__.py
pyeuropeana/apis/entity.py
pyeuropeana/apis/iiif.py
pyeuropeana/apis/record.py
pyeuropeana/apis/search.py
pyeuropeana/utils/__init__.py
pyeuropeana/utils/auth.py
pyeuropeana/utils/edm_utils.py
pyeuropeana/utils/img_utils.py
pyeuropeana-0.1.7.dist-info/LICENSE.md
pyeuropeana-0.1.7.dist-info/WHEEL
pyeuropeana-0.1.7.dist-info/METADATA
pyeuropeana-0.1.7.dist-info/RECORD
