Metadata-Version: 2.1
Name: pyeuropeana
Version: 0.1.7
Summary: A Python wrapper around Europeana APIs
Home-page: https://github.com/europeana/rd-europeana-python-api
License: European Union Public Licence v. 1.2
Keywords: GLAM,europeana,cultural heritage
Author: José Eduardo Cejudo Grano de Oro
Author-email: joseed.cejudo@europeana.eu
Requires-Python: >=3.7,<4.0
Classifier: Intended Audience :: Developers
Classifier: Intended Audience :: Information Technology
Classifier: Intended Audience :: Science/Research
Classifier: License :: Other/Proprietary License
Classifier: Operating System :: OS Independent
Classifier: Programming Language :: Python :: 3
Classifier: Programming Language :: Python :: 3.10
Classifier: Programming Language :: Python :: 3.7
Classifier: Programming Language :: Python :: 3.8
Classifier: Programming Language :: Python :: 3.9
Classifier: Topic :: Software Development :: Libraries :: Python Modules
Requires-Dist: fire (>=0.4,<0.5)
Requires-Dist: pandas (>=1.3,<2.0)
Requires-Dist: requests (>=2.27,<3.0)
Project-URL: Repository, https://github.com/europeana/rd-europeana-python-api
